gex/Timer.py
gex/__init__.py
gex/__main__.py
gex/extra/NetworkList.py
gex/extra/construct_pp_db.py
gex/extra/gex.svg
gex/extra/this.txt
gex/gui.py
gex/io.py
gex/paint.py
gex-0.1.1.dist-info/METADATA
gex-0.1.1.dist-info/WHEEL
gex-0.1.1.dist-info/entry_points.txt
gex-0.1.1.dist-info/RECORD
